nanodt/__init__.py
nanodt/agent.py
nanodt/model.py
nanodt/py.typed
nanodt/trainer.py
nanodt/utils.py
nanodt-0.1.0.dist-info/METADATA
nanodt-0.1.0.dist-info/WHEEL
nanodt-0.1.0.dist-info/licenses/LICENSE
nanodt-0.1.0.dist-info/RECORD
