Metadata-Version: 2.4
Name: nanodt
Version: 0.1.0
Summary: A minimal Decision Transformer implementation for Minari datasets.
Project-URL: Homepage, https://github.com/lubiluk/nanoDTm
Project-URL: Repository, https://github.com/lubiluk/nanoDT
Project-URL: Issues, https://github.com/lubiluk/nanoDT/issues
Author-email: Paul Gajewski <lubiluk@gmail.com>
License: MIT License
License-File: LICENSE
Requires-Python: >=3.12
Requires-Dist: gymnasium>=1.1.1
Requires-Dist: minari[hdf5]>=0.5.3
Requires-Dist: numpy>=2.2.5
Requires-Dist: pillow>=11.2.1
Requires-Dist: torch>=2.7.0
